unscribe/__init__.py
unscribe/main.py
unscribe/refiner.py
unscribe/utils.py
unscribe/saicinpainting/__init__.py
unscribe/saicinpainting/utils.py
unscribe/saicinpainting/evaluation/__init__.py
unscribe/saicinpainting/evaluation/data.py
unscribe/saicinpainting/evaluation/evaluator.py
unscribe/saicinpainting/evaluation/refinement.py
unscribe/saicinpainting/evaluation/utils.py
unscribe/saicinpainting/evaluation/vis.py
unscribe/saicinpainting/evaluation/losses/__init__.py
unscribe/saicinpainting/evaluation/losses/base_loss.py
unscribe/saicinpainting/evaluation/losses/lpips.py
unscribe/saicinpainting/evaluation/losses/ssim.py
unscribe/saicinpainting/evaluation/losses/fid/__init__.py
unscribe/saicinpainting/evaluation/losses/fid/fid_score.py
unscribe/saicinpainting/evaluation/losses/fid/inception.py
unscribe/saicinpainting/evaluation/masks/__init__.py
unscribe/saicinpainting/evaluation/masks/mask.py
unscribe/saicinpainting/evaluation/masks/countless/__init__.py
unscribe/saicinpainting/evaluation/masks/countless/countless2d.py
unscribe/saicinpainting/evaluation/masks/countless/countless3d.py
unscribe/saicinpainting/evaluation/masks/countless/test.py
unscribe/saicinpainting/training/__init__.py
unscribe/saicinpainting/training/data/__init__.py
unscribe/saicinpainting/training/data/aug.py
unscribe/saicinpainting/training/data/datasets.py
unscribe/saicinpainting/training/data/masks.py
unscribe/saicinpainting/training/losses/__init__.py
unscribe/saicinpainting/training/losses/adversarial.py
unscribe/saicinpainting/training/losses/constants.py
unscribe/saicinpainting/training/losses/distance_weighting.py
unscribe/saicinpainting/training/losses/feature_matching.py
unscribe/saicinpainting/training/losses/perceptual.py
unscribe/saicinpainting/training/losses/segmentation.py
unscribe/saicinpainting/training/losses/style_loss.py
unscribe/saicinpainting/training/modules/__init__.py
unscribe/saicinpainting/training/modules/base.py
unscribe-0.0.4.dist-info/LICENSE
unscribe-0.0.4.dist-info/METADATA
unscribe-0.0.4.dist-info/WHEEL
unscribe-0.0.4.dist-info/top_level.txt
unscribe-0.0.4.dist-info/RECORD
