Metadata-Version: 2.1
Name: unscribe
Version: 0.0.4
Summary: A straightforward text remover and/or scrambler using LaMa inpainting and CRAFT text-detection
Home-page: https://github.com/manbehindthemadness/modern-craft
Author: Manbehindthemadness
Author-email: manbehindthemadness@gmail.com
Classifier: Programming Language :: Python :: 3
Classifier: License :: OSI Approved :: MIT License
Classifier: Operating System :: OS Independent
Requires-Python: >=3.10
License-File: LICENSE
Requires-Dist: pyyaml
Requires-Dist: tqdm
Requires-Dist: numpy <2.0.0
Requires-Dist: omegaconf
Requires-Dist: easydict >=1.9.0
Requires-Dist: scikit-image >=0.17.2
Requires-Dist: scikit-learn >=0.24.2
Requires-Dist: joblib
Requires-Dist: Pillow
Requires-Dist: matplotlib
Requires-Dist: mcraft >0.0.4
Requires-Dist: pandas
Requires-Dist: albumentations >=0.5.2
Requires-Dist: hydra-core >=1.1.0
Requires-Dist: tabulate
Requires-Dist: webdataset
Requires-Dist: packaging
Requires-Dist: wldhx.yadisk-direct
Requires-Dist: tensorflow
Requires-Dist: opencv-python >=3.4.2.17
Requires-Dist: torch >=2.0.0
Requires-Dist: pytorch-lightning ==1.2.9
Requires-Dist: kornia ==0.5.0
Requires-Dist: torchvision >=0.17.0
Requires-Dist: quickdl
